src/__init__.py
src/detector.py
src/report_generator.py
src/utils.py
tests/__init__.py
tests/test_detector.py
tests/test_report_generator.py
simple_dns_poisoning_detector-1.0.dist-info/LICENSE
simple_dns_poisoning_detector-1.0.dist-info/METADATA
simple_dns_poisoning_detector-1.0.dist-info/WHEEL
simple_dns_poisoning_detector-1.0.dist-info/entry_points.txt
simple_dns_poisoning_detector-1.0.dist-info/top_level.txt
simple_dns_poisoning_detector-1.0.dist-info/RECORD
