Metadata-Version: 2.1
Name: simple-dns-poisoning-detector
Version: 1.0
Summary: A tool to detect DNS poisoning attacks.
Home-page: https://github.com/akintunero/dns-poisoning-detector
Author: Olúmáyòwá Akinkuehinmi
Author-email: akintunero101@gmail.com
Classifier: Programming Language :: Python :: 3
Classifier: License :: OSI Approved :: MIT License
Classifier: Operating System :: OS Independent
Classifier: Topic :: Security
Classifier: Topic :: System :: Networking :: Monitoring
Requires-Python: >=3.6
License-File: LICENSE
Requires-Dist: scapy
Requires-Dist: reportlab
Requires-Dist: PyYAML
